microalpha/__init__.py
microalpha/backtest.py
microalpha/data_fetcher.py
microalpha/enhanced.py
microalpha/features.py
microalpha/io.py
microalpha/simple.py
microalpha-0.2.2.dist-info/licenses/LICENSE
microalpha-0.2.2.dist-info/METADATA
microalpha-0.2.2.dist-info/WHEEL
microalpha-0.2.2.dist-info/top_level.txt
microalpha-0.2.2.dist-info/RECORD
