Metadata-Version: 2.4
Name: microalpha
Version: 0.2.2
Summary: A Python library for analyzing ultra-high-frequency tick data and discovering micro-alpha trading signals.
Author: Amaya Joshi
License: MIT
Project-URL: Homepage, https://github.com/amaya-j/MicroAlpha.git
Project-URL: Issues, https://github.com/amaya-j/MicroAlpha.git/issues
Requires-Python: >=3.9
License-File: LICENSE
Requires-Dist: pandas>=1.5
Requires-Dist: numpy>=1.21
Provides-Extra: eda
Requires-Dist: matplotlib>=3.5; extra == "eda"
Requires-Dist: seaborn>=0.11; extra == "eda"
Dynamic: license-file
